DAY2/four_mux/four_mux.v
module four_mux(out,a,b,c,d,s0,s1);
input a,b,c,d;
input s0,s1;
output out;
assign out=(~s0&~s1&a)|(~s0&s1&b)|(s0&~s1&c)|(s0&s1&d);
endmodule

DAY2/four_mux/four_mux_tb.v
module four_mux_tb;
reg a,b,c,d,s0,s1;
wire out;

four_mux uut(.a(a),.b(b),.c(c),.d(d),.s0(s0),.s1(s1),.out(out));

initial begin
$monitor("Time=%0t a=%b b=%b c=%b d=%b s0=%b s1=%b out=%b",$time,a,b,c,d,s0,s1,out);
$dumpfile("four_mux_wave.vcd");
$dumpvars(0,four_mux_tb);


   a=0;b=0;c=0;d=0;s0=0;s1=0;
#5 a=0;b=0;c=0;d=1;s0=0;s1=1;
#5 a=0;b=0;c=1;d=0;s0=1;s1=0;
#5 a=0;b=0;c=1;d=1;s0=1;s1=1;
#5 a=0;b=1;c=0;d=0;s0=0;s1=0;
#5 a=0;b=1;c=0;d=1;s0=0;s1=1;
#5 a=0;b=1;c=1;d=0;s0=1;s1=0;
#5 a=0;b=1;c=1;d=1;s0=1;s1=1;
#5 a=1;b=0;c=0;d=0;s0=0;s1=0;
#5 a=1;b=0;c=0;d=1;s0=0;s1=1;
#5 a=1;b=0;c=1;d=0;s0=1;s1=0;
#5 a=1;b=0;c=1;d=1;s0=1;s1=1;
#5 a=1;b=1;c=0;d=0;s0=0;s1=0;
#5 a=1;b=1;c=0;d=1;s0=0;s1=1;
#5 a=1;b=1;c=1;d=0;s0=1;s1=0;
#5 a=1;b=1;c=1;d=1;s0=1;s1=1;
$finish;
end
endmodule

DAY2/four_mux/four_mux_wave.vcd
$date
	Sat Oct 11 06:19:26 2025
$end
$version
	Icarus Verilog
$end
$timescale
	1s
$end
$scope module four_mux_tb $end
$var wire 1 ! out $end
$var reg 1 " a $end
$var reg 1 # b $end
$var reg 1 $ c $end
$var reg 1 % d $end
$var reg 1 & s0 $end
$var reg 1 ' s1 $end
$scope module uut $end
$var wire 1 " a $end
$var wire 1 # b $end
$var wire 1 $ c $end
$var wire 1 % d $end
$var wire 1 ! out $end
$var wire 1 & s0 $end
$var wire 1 ' s1 $end
$upscope $end
$upscope $end
$enddefinitions $end
$comment Show the parameter values. $end
$dumpall
$end
#0
$dumpvars
0'
0&
0%
0$
0#
0"
0!
$end
#5
1'
1%
#10
1!
0'
1&
0%
1$
#15
1'
1%
#20
0!
0'
0&
0%
0$
1#
#25
1!
1'
1%
#30
0'
1&
0%
1$
#35
1'
1%
#40
1!
0'
0&
0%
0$
0#
1"
#45
0!
1'
1%
#50
1!
0'
1&
0%
1$
#55
1'
1%
#60
1!
0'
0&
0%
0$
1#
#65
1'
1%
#70
0'
1&
0%
1$
#75
1'
1%
