DAY1/full_adder/full_adder.v
module full_adder(input a,b,cin,output sum,carry);
xor (a1,a,b);
xor (sum,a1,cin);
and (b1,a1,cin);
and (c1,a,b);
or (carry,b1,c1);

endmodule

DAY2/full_adder/full_adder_tb.v
module full_adder_tb();
reg a,b,cin;
wire sum,carry;

full_adder dut(.a(a),.b(b),.cin(cin),.sum(sum),.carry(carry));

initial begin
$monitor("Time=%0t a=%b b=%b cin=%b sum=%b carry=%b",$time,a,b,cin,sum,carry);
$dumpfile("full_adder_wave.vcd");
$dumpvars(8,full_adder_tb);

a=0;b=0;cin=0;
#10 a=0;b=0;cin=1;
#10 a=0;b=1;cin=0;
#10 a=0;b=1;cin=1;
#10 a=1;b=0;cin=0;
#10 a=1;b=0;cin=1;
#10 a=1;b=1;cin=0;
#10 a=1;b=1;cin=1;
#10;
$finish;
end
endmodule

DAY2/full_adder/full_adder_wave.vcd
$date
	Fri Oct 10 04:27:07 2025
$end
$version
	Icarus Verilog
$end
$timescale
	1s
$end
$scope module full_adder_tb $end
$var wire 1 ! sum $end
$var wire 1 " carry $end
$var reg 1 # a $end
$var reg 1 $ b $end
$var reg 1 % cin $end
$scope module dut $end
$var wire 1 # a $end
$var wire 1 $ b $end
$var wire 1 " carry $end
$var wire 1 % cin $end
$var wire 1 ! sum $end
$upscope $end
$upscope $end
$enddefinitions $end
$comment Show the parameter values. $end
$dumpall
$end
#0
$dumpvars
0%
0$
0#
0"
0!
$end
#10
1!
1%
#20
0%
1$
#30
1"
0!
1%
#40
0"
1!
0%
0$
1#
#50
1"
0!
1%
#60
0%
1$
#70
1!
1%
