DAY3/eight_bit_comparator/eight_bit_comparator.v
module eight_bit_comparator(x,y,z,a,b);
input [7:0] a,b;
output x,y,z;

assign x= a>b;
assign y= a<b;
assign z= a==b;

endmodule

DAY3/eight_bit_comparator/eight_bit_comparator_tb.v
module eight_bit_comparator_tb;

reg [7:0]a;
reg [7:0]b;
wire x,y,z;
integer i,j;

eight_bit_comparator dut(.x(x),.y(y),.z(z),.a(a),.b(b));

initial begin
	$monitor("a=%b b=%b x(a>b)=%b y(a<b)=%b z(a==b)=%b",a,b,x,y,z);
	$dumpfile("eight_bit_comparator_wave.vcd");
	$dumpvars(0,eight_bit_comparator_tb);

	for(i=0;i<256;i=i+1)begin 
		for(j=0;j<256;j=j+1)begin
	a=i;
        b=j; #5;
end
end
$finish;
end
endmodule

DAY3/eight_bit_comparator/eight_bit_comparator_wave.vcd
$date
	Mon Oct 13 05:45:54 2025
$end
$version
	Icarus Verilog
$end
$timescale
	1s
$end
$scope module eight_bit_comparator_tb $end
$var wire 1 ! z $end
$var wire 1 " y $end
$var wire 1 # x $end
$var reg 8 $ a [7:0] $end
$var reg 8 % b [7:0] $end
$var integer 32 & i [31:0] $end
$var integer 32 ' j [31:0] $end
$scope module dut $end
$var wire 8 ( a [7:0] $end
$var wire 8 ) b [7:0] $end
$var wire 1 ! z $end
$var wire 1 " y $end
$var wire 1 # x $end
$upscope $end
$upscope $end
$enddefinitions $end
$comment Show the parameter values. $end
$dumpall
$end
#0
$dumpvars
b0 )
b0 (
b0 '
b0 &
b0 %
b0 $
0#
0"
1!
$end
#5
1"
0!
b1 %
b1 )
b1 '
#10
b10 %
b10 )
b10 '
#15
b11 %
b11 )
b11 '
#20
b100 %
b100 )
b100 '
#25
b101 %
b101 )
b101 '
#30
b110 %
b110 )
b110 '
#35
b111 %
b111 )
b111 '
#40
b1000 %
b1000 )
b1000 '
#45
b1001 %
b1001 )
b1001 '
#50
b1010 %
b1010 )
b1010 '
#55
b1011 %
b1011 )
b1011 '
#60
b1100 %
b1100 )
b1100 '
#65
b1101 %
b1101 )
b1101 '
#70
b1110 %
b1110 )
b1110 '
#75
b1111 %
b1111 )
b1111 '
#80
b10000 %
b10000 )
b10000 '
#85
b10001 %
b10001 )
b10001 '
#90
b10010 %
b10010 )
b10010 '
#95
b10011 %
b10011 )
b10011 '
#100
b10100 %
b10100 )
b10100 '
#105
b10101 %
b10101 )
b10101 '
#110
b10110 %
b10110 )
b10110 '
#115
b10111 %
b10111 )
b10111 '
#120
b11000 %
b11000 )
b11000 '
#125
b11001 %
b11001 )
b11001 '
#130
b11010 %
b11010 )
b11010 '
#135
b11011 %
b11011 )
b11011 '
#140
b11100 %
b11100 )
b11100 '
#145
b11101 %
b11101 )
b11101 '
#150
b11110 %
b11110 )
b11110 '
#155
b11111 %
b11111 )
b11111 '
#160
b100000 %
b100000 )
b100000 '
#165
b100001 %
b100001 )
b100001 '
#170
b100010 %
b100010 )
b100010 '
#175
b100011 %
b100011 )
b100011 '
#180
b100100 %
b100100 )
b100100 '
#185
b100101 %
b100101 )
b100101 '
#190
b100110 %
b100110 )
b100110 '
#195
b100111 %
b100111 )
b100111 '
#200
b101000 %
b101000 )
b101000 '
#205
b101001 %
b101001 )
b101001 '
#210
b101010 %
b101010 )
b101010 '
#215
b101011 %
b101011 )
b101011 '
#220
b101100 %
b101100 )
b101100 '
#225
b101101 %
b101101 )
b101101 '
#230
b101110 %
b101110 )
b101110 '
#235
b101111 %
b101111 )
b101111 '
#240
b110000 %
b110000 )
b110000 '
#245
b110001 %
b110001 )
b110001 '
#250
b110010 %
b110010 )
b110010 '
#255
b110011 %
b110011 )
b110011 '
#260
b110100 %
b110100 )
b110100 '
#265
b110101 %
b110101 )
b110101 '
#270
b110110 %
b110110 )
b110110 '
#275
b110111 %
b110111 )
b110111 '
#280
b111000 %
b111000 )
b111000 '
#285
b111001 %
b111001 )
b111001 '
#290
b111010 %
b111010 )
b111010 '
#295
b111011 %
b111011 )
b111011 '
#300
b111100 %
b111100 )
b111100 '
#305
b111101 %
b111101 )
b111101 '
#310
b111110 %
b111110 )
b111110 '
#315
b111111 %
b111111 )
b111111 '
#320
b1000000 %
b1000000 )
b1000000 '
#325
b1000001 %
b1000001 )
b1000001 '
#330
b1000010 %
b1000010 )
b1000010 '
#335
b1000011 %
b1000011 )
b1000011 '
#340
b1000100 %
b1000100 )
b1000100 '
#345
b1000101 %
b1000101 )
b1000101 '
#350
b1000110 %
b1000110 )
b1000110 '
#355
b1000111 %
b1000111 )
b1000111 '
#360
b1001000 %
b1001000 )
b1001000 '
#365
b1001001 %
b1001001 )
b1001001 '
#370
b1001010 %
b1001010 )
b1001010 '
#375
b1001011 %
b1001011 )
b1001011 '
#380
b1001100 %
b1001100 )
b1001100 '
#385
b1001101 %
b1001101 )
b1001101 '
#390
b1001110 %
b1001110 )
b1001110 '
#395
b1001111 %
b1001111 )
b1001111 '
#400
b1010000 %
b1010000 )
b1010000 '
#405
b1010001 %
b1010001 )
b1010001 '
#410
b1010010 %
b1010010 )
b1010010 '
#415
b1010011 %
b1010011 )
b1010011 '
#420
b1010100 %
b1010100 )
b1010100 '
#425
b1010101 %
b1010101 )
b1010101 '
#430
b1010110 %
b1010110 )
b1010110 '
#435
b1010111 %
b1010111 )
b1010111 '
#440
b1011000 %
b1011000 )
b1011000 '
#445
b1011001 %
b1011001 )
b1011001 '
#450
b1011010 %
b1011010 )
b1011010 '
#455
b1011011 %
b1011011 )
b1011011 '
#460
b1011100 %
b1011100 )
b1011100 '
#465
b1011101 %
b1011101 )
b1011101 '
#470
b1011110 %
b1011110 )
b1011110 '
#475
b1011111 %
b1011111 )
b1011111 '
#480
b1100000 %
b1100000 )
b1100000 '
#485
b1100001 %
b1100001 )
b1100001 '
#490
b1100010 %
b1100010 )
b1100010 '
#495
b1100011 %
b1100011 )
b1100011 '
#500
b1100100 %
b1100100 )
b1100100 '
#505
b1100101 %
b1100101 )
b1100101 '
#510
b1100110 %
b1100110 )
b1100110 '
#515
b1100111 %
b1100111 )
b1100111 '
#520
b1101000 %
b1101000 )
b1101000 '
#525
b1101001 %
b1101001 )
b1101001 '
#530
b1101010 %
b1101010 )
b1101010 '
#535
b1101011 %
b1101011 )
b1101011 '
#540
b1101100 %
b1101100 )
b1101100 '
#545
b1101101 %
b1101101 )
b1101101 '
#550
b1101110 %
b1101110 )
b1101110 '
#555
b1101111 %
b1101111 )
b1101111 '
#560
b1110000 %
b1110000 )
b1110000 '
#565
b1110001 %
b1110001 )
b1110001 '
#570
b1110010 %
b1110010 )
b1110010 '
#575
b1110011 %
b1110011 )
b1110011 '
#580
b1110100 %
b1110100 )
b1110100 '
#585
b1110101 %
b1110101 )
b1110101 '
#590
b1110110 %
b1110110 )
b1110110 '
#595
b1110111 %
b1110111 )
b1110111 '
#600
b1111000 %
b1111000 )
b1111000 '
#605
b1111001 %
b1111001 )
b1111001 '
#610
b1111010 %
b1111010 )
b1111010 '
#615
b1111011 %
b1111011 )
b1111011 '
#620
b1111100 %
b1111100 )
b1111100 '
#625
b1111101 %
b1111101 )
b1111101 '
#630
b1111110 %
b1111110 )
b1111110 '
#635
b1111111 %
b1111111 )
b1111111 '
#640
b10000000 %
b10000000 )
b10000000 '
#645
b10000001 %
b10000001 )
b10000001 '
#650
b10000010 %
b10000010 )
b10000010 '
#655
b10000011 %
b10000011 )
b10000011 '
#660
b10000100 %
b10000100 )
b10000100 '
#665
b10000101 %
b10000101 )
b10000101 '
#670
b10000110 %
b10000110 )
b10000110 '
#675
b10000111 %
b10000111 )
b10000111 '
#680
b10001000 %
b10001000 )
b10001000 '
#685
b10001001 %
b10001001 )
b10001001 '
#690
b10001010 %
b10001010 )
b10001010 '
#695
b10001011 %
b10001011 )
b10001011 '
#700
b10001100 %
b10001100 )
b10001100 '
#705
b10001101 %
b10001101 )
b10001101 '
#710
b10001110 %
b10001110 )
b10001110 '
#715
b10001111 %
b10001111 )
b10001111 '
#720
b10010000 %
b10010000 )
b10010000 '
#725
b10010001 %
b10010001 )
b10010001 '
#730
b10010010 %
b10010010 )
b10010010 '
#735
b10010011 %
b10010011 )
b10010011 '
#740
b10010100 %
b10010100 )
b10010100 '
#745
b10010101 %
b10010101 )
b10010101 '
#750
b10010110 %
b10010110 )
b10010110 '
#755
b10010111 %
b10010111 )
b10010111 '
#760
b10011000 %
b10011000 )
b10011000 '
#765
b10011001 %
b10011001 )
b10011001 '
#770
b10011010 %
b10011010 )
b10011010 '
#775
b10011011 %
b10011011 )
b10011011 '
#780
b10011100 %
b10011100 )
b10011100 '
#785
b10011101 %
b10011101 )
b10011101 '
#790
b10011110 %
b10011110 )
b10011110 '
#795
b10011111 %
b10011111 )
b10011111 '
#800
b10100000 %
b10100000 )
b10100000 '
#805
b10100001 %
b10100001 )
b10100001 '
#810
b10100010 %
b10100010 )
b10100010 '
#815
b10100011 %
b10100011 )
b10100011 '
#820
b10100100 %
b10100100 )
b10100100 '
#825
b10100101 %
b10100101 )
b10100101 '
#830
b10100110 %
b10100110 )
b10100110 '
#835
b10100111 %
b10100111 )
b10100111 '
#840
b10101000 %
b10101000 )
b10101000 '
#845
b10101001 %
b10101001 )
b10101001 '
#850
b10101010 %
b10101010 )
b10101010 '
#855
b10101011 %
b10101011 )
b10101011 '
#860
b10101100 %
b10101100 )
b10101100 '
#865
b10101101 %
b10101101 )
b10101101 '
#870
b10101110 %
b10101110 )
b10101110 '
#875
b10101111 %
b10101111 )
b10101111 '
#880
b10110000 %
b10110000 )
b10110000 '
#885
b10110001 %
b10110001 )
b10110001 '
#890
b10110010 %
b10110010 )
b10110010 '
#895
b10110011 %
b10110011 )
b10110011 '
#900
b10110100 %
b10110100 )
b10110100 '
#905
b10110101 %
b10110101 )
b10110101 '
#910
b10110110 %
b10110110 )
b10110110 '
#915
b10110111 %
b10110111 )
b10110111 '
#920
b10111000 %
b10111000 )
b10111000 '
#925
b10111001 %
b10111001 )
b10111001 '
#930
b10111010 %
b10111010 )
b10111010 '
#935
b10111011 %
b10111011 )
b10111011 '
#940
b10111100 %
b10111100 )
b10111100 '
#945
b10111101 %
b10111101 )
b10111101 '
#950
b10111110 %
b10111110 )
b10111110 '
#955
b10111111 %
b10111111 )
b10111111 '
#960
b11000000 %
b11000000 )
b11000000 '
#965
b11000001 %
b11000001 )
b11000001 '
#970
b11000010 %
b11000010 )
b11000010 '
#975
b11000011 %
b11000011 )
b11000011 '
#980
b11000100 %
b11000100 )
b11000100 '
#985
b11000101 %
b11000101 )
b11000101 '
#990
b11000110 %
b11000110 )
b11000110 '
#995
b11000111 %
b11000111 )
b11000111 '
#1000
b11001000 %
b11001000 )
b11001000 '
#1005
b11001001 %
b11001001 )
b11001001 '
#1010
b11001010 %
b11001010 )
b11001010 '
#1015
b11001011 %
b11001011 )
b11001011 '
#1020
b11001100 %
b11001100 )
b11001100 '
#1025
b11001101 %
b11001101 )
b11001101 '
#1030
b11001110 %
b11001110 )
b11001110 '
#1035
b11001111 %
b11001111 )
b11001111 '
#1040
b11010000 %
b11010000 )
b11010000 '
#1045
b11010001 %
b11010001 )
b11010001 '
#1050
b11010010 %
b11010010 )
b11010010 '
#1055
b11010011 %
b11010011 )
b11010011 '
#1060
b11010100 %
b11010100 )
b11010100 '
#1065
b11010101 %
b11010101 )
b11010101 '
#1070
b11010110 %
b11010110 )
b11010110 '
#1075
b11010111 %
b11010111 )
b11010111 '
#1080
b11011000 %
b11011000 )
b11011000 '
#1085
b11011001 %
b11011001 )
b11011001 '
#1090
b11011010 %
b11011010 )
b11011010 '
#1095
b11011011 %
b11011011 )
b11011011 '
#1100
b11011100 %
b11011100 )
b11011100 '
#1105
b11011101 %
b11011101 )
b11011101 '
#1110
b11011110 %
b11011110 )
b11011110 '
#1115
b11011111 %
b11011111 )
b11011111 '
#1120
b11100000 %
b11100000 )
b11100000 '
#1125
b11100001 %
b11100001 )
b11100001 '
#1130
b11100010 %
b11100010 )
b11100010 '
#1135
b11100011 %
b11100011 )
b11100011 '
#1140
b11100100 %
b11100100 )
b11100100 '
#1145
b11100101 %
b11100101 )
b11100101 '
#1150
b11100110 %
b11100110 )
b11100110 '
#1155
b11100111 %
b11100111 )
b11100111 '
#1160
b11101000 %
b11101000 )
b11101000 '
#1165
b11101001 %
b11101001 )
b11101001 '
#1170
b11101010 %
b11101010 )
b11101010 '
#1175
b11101011 %
b11101011 )
b11101011 '
#1180
b11101100 %
b11101100 )
b11101100 '
#1185
b11101101 %
b11101101 )
b11101101 '
#1190
b11101110 %
b11101110 )
b11101110 '
#1195
b11101111 %
b11101111 )
b11101111 '
#1200
b11110000 %
b11110000 )
b11110000 '
#1205
b11110001 %
b11110001 )
b11110001 '
#1210
b11110010 %
b11110010 )
b11110010 '
#1215
b11110011 %
b11110011 )
b11110011 '
#1220
b11110100 %
b11110100 )
b11110100 '
#1225
b11110101 %
b11110101 )
b11110101 '
#1230
b11110110 %
b11110110 )
b11110110 '
#1235
b11110111 %
b11110111 )
b11110111 '
#1240
b11111000 %
b11111000 )
b11111000 '
#1245
b11111001 %
b11111001 )
b11111001 '
#1250
b11111010 %
b11111010 )
b11111010 '
#1255
b11111011 %
b11111011 )
b11111011 '
#1260
b11111100 %
b11111100 )
b11111100 '
#1265
b11111101 %
b11111101 )
b11111101 '
#1270
b11111110 %
b11111110 )
b11111110 '
#1275
b11111111 %
b11111111 )
b11111111 '
#1280
1#
0"
b0 %
b0 )
b1 $
b1 (
b1 &
b0 '
#1285
0#
1!
b1 %
b1 )
b1 '
#1290
1"
0!
b10 %
b10 )
b10 '
#1295
b11 %
b11 )
b11 '
#1300
b100 %
b100 )
b100 '
#1305
b101 %
b101 )
b101 '
#1310
b110 %
b110 )
b110 '
#1315
b111 %
b111 )
b111 '
#1320
b1000 %
b1000 )
b1000 '
#1325
b1001 %
b1001 )
b1001 '
#1330
b1010 %
b1010 )
b1010 '
#1335
b1011 %
b1011 )
b1011 '
#1340
b1100 %
b1100 )
b1100 '
#1345
b1101 %
b1101 )
b1101 '
#1350
b1110 %
b1110 )
b1110 '
#1355
b1111 %
b1111 )
b1111 '
#1360
b10000 %
b10000 )
b10000 '
#1365
b10001 %
b10001 )
b10001 '
#1370
b10010 %
b10010 )
b10010 '
#1375
b10011 %
b10011 )
b10011 '
#1380
b10100 %
b10100 )
b10100 '
#1385
b10101 %
b10101 )
b10101 '
#1390
b10110 %
b10110 )
b10110 '
#1395
b10111 %
b10111 )
b10111 '
#1400
b11000 %
b11000 )
b11000 '
#1405
b11001 %
b11001 )
b11001 '
#1410
b11010 %
b11010 )
b11010 '
#1415
b11011 %
b11011 )
b11011 '
#1420
b11100 %
b11100 )
b11100 '
#1425
b11101 %
b11101 )
b11101 '
#1430
b11110 %
b11110 )
b11110 '
#1435
b11111 %
b11111 )
b11111 '
#1440
b100000 %
b100000 )
b100000 '
#1445
b100001 %
b100001 )
b100001 '
#1450
b100010 %
b100010 )
b100010 '
#1455
b100011 %
b100011 )
b100011 '
#1460
b100100 %
b100100 )
b100100 '
#1465
b100101 %
b100101 )
b100101 '
#1470
b100110 %
b100110 )
b100110 '
#1475
b100111 %
b100111 )
b100111 '
#1480
b101000 %
b101000 )
b101000 '
#1485
b101001 %
b101001 )
b101001 '
#1490
b101010 %
b101010 )
b101010 '
#1495
b101011 %
b101011 )
b101011 '
#1500
b101100 %
b101100 )
b101100 '
#1505
b101101 %
b101101 )
b101101 '
#1510
b101110 %
b101110 )
b101110 '
#1515
b101111 %
b101111 )
b101111 '
#1520
b110000 %
b110000 )
b110000 '
#1525
b110001 %
b110001 )
b110001 '
#1530
b110010 %
b110010 )
b110010 '
#1535
b110011 %
b110011 )
b110011 '
#1540
b110100 %
b110100 )
b110100 '
#1545
b110101 %
b110101 )
b110101 '
#1550
b110110 %
b110110 )
b110110 '
#1555
b110111 %
b110111 )
b110111 '
#1560
b111000 %
b111000 )
b111000 '
#1565
b111001 %
b111001 )
b111001 '
#1570
b111010 %
b111010 )
b111010 '
#1575
b111011 %
b111011 )
b111011 '
#1580
b111100 %
b111100 )
b111100 '
#1585
b111101 %
b111101 )
b111101 '
#1590
b111110 %
b111110 )
b111110 '
#1595
b111111 %
b111111 )
b111111 '
#1600
b1000000 %
b1000000 )
b1000000 '
#1605
b1000001 %
b1000001 )
b1000001 '
#1610
b1000010 %
b1000010 )
b1000010 '
#1615
b1000011 %
b1000011 )
b1000011 '
#1620
b1000100 %
b1000100 )
b1000100 '
#1625
b1000101 %
b1000101 )
b1000101 '
#1630
b1000110 %
b1000110 )
b1000110 '
#1635
b1000111 %
b1000111 )
b1000111 '
#1640
b1001000 %
b1001000 )
b1001000 '
#1645
b1001001 %
b1001001 )
b1001001 '
#1650
b1001010 %
b1001010 )
b1001010 '
#1655
b1001011 %
b1001011 )
b1001011 '
#1660
b1001100 %
b1001100 )
b1001100 '
#1665
b1001101 %
b1001101 )
b1001101 '
#1670
b1001110 %
b1001110 )
b1001110 '
#1675
b1001111 %
b1001111 )
b1001111 '
#1680
b1010000 %
b1010000 )
b1010000 '
#1685
b1010001 %
b1010001 )
b1010001 '
#1690
b1010010 %
b1010010 )
b1010010 '
#1695
b1010011 %
b1010011 )
b1010011 '
#1700
b1010100 %
b1010100 )
b1010100 '
#1705
b1010101 %
b1010101 )
b1010101 '
#1710
b1010110 %
b1010110 )
b1010110 '
#1715
b1010111 %
b1010111 )
b1010111 '
#1720
b1011000 %
b1011000 )
b1011000 '
#1725
b1011001 %
b1011001 )
b1011001 '
#1730
b1011010 %
b1011010 )
b1011010 '
#1735
b1011011 %
b1011011 )
b1011011 '
#1740
b1011100 %
b1011100 )
b1011100 '
#1745
b1011101 %
b1011101 )
b1011101 '
#1750
b1011110 %
b1011110 )
b1011110 '
#1755
b1011111 %
b1011111 )
b1011111 '
#1760
b1100000 %
b1100000 )
b1100000 '
#1765
b1100001 %
b1100001 )
b1100001 '
#1770
b1100010 %
b1100010 )
b1100010 '
#1775
b1100011 %
b1100011 )
b1100011 '
#1780
b1100100 %
b1100100 )
b1100100 '
#1785
b1100101 %
b1100101 )
b1100101 '
#1790
b1100110 %
b1100110 )
b1100110 '
#1795
b1100111 %
b1100111 )
b1100111 '
#1800
b1101000 %
b1101000 )
b1101000 '
#1805
b1101001 %
b1101001 )
b1101001 '
#1810
b1101010 %
b1101010 )
b1101010 '
#1815
b1101011 %
b1101011 )
b1101011 '
#1820
b1101100 %
b1101100 )
b1101100 '
#1825
b1101101 %
b1101101 )
b1101101 '
#1830
b1101110 %
b1101110 )
b1101110 '
#1835
b1101111 %
b1101111 )
b1101111 '
#1840
b1110000 %
b1110000 )
b1110000 '
#1845
b1110001 %
b1110001 )
b1110001 '
#1850
b1110010 %
b1110010 )
b1110010 '
#1855
b1110011 %
b1110011 )
b1110011 '
#1860
b1110100 %
b1110100 )
b1110100 '
#1865
b1110101 %
b1110101 )
b1110101 '
#1870
b1110110 %
b1110110 )
b1110110 '
#1875
b1110111 %
b1110111 )
b1110111 '
#1880
b1111000 %
b1111000 )
b1111000 '
#1885
b1111001 %
b1111001 )
b1111001 '
#1890
b1111010 %
b1111010 )
b1111010 '
#1895
b1111011 %
b1111011 )
b1111011 '
#1900
b1111100 %
b1111100 )
b1111100 '
#1905
b1111101 %
b1111101 )
b1111101 '
#1910
b1111110 %
b1111110 )
b1111110 '
#1915
b1111111 %
b1111111 )
b1111111 '
#1920
b10000000 %
b10000000 )
b10000000 '
#1925
b10000001 %
b10000001 )
b10000001 '
#1930
b10000010 %
b10000010 )
b10000010 '
#1935
b10000011 %
b10000011 )
b10000011 '
#1940
b10000100 %
b10000100 )
b10000100 '
#1945
b10000101 %
b10000101 )
b10000101 '
#1950
b10000110 %
b10000110 )
b10000110 '
#1955
b10000111 %
b10000111 )
b10000111 '
#1960
b10001000 %
b10001000 )
b10001000 '
#1965
b10001001 %
b10001001 )
b10001001 '
#1970
b10001010 %
b10001010 )
b10001010 '
#1975
b10001011 %
b10001011 )
b10001011 '
#1980
b10001100 %
b10001100 )
b10001100 '
#1985
b10001101 %
b10001101 )
b10001101 '
#1990
b10001110 %
b10001110 )
b10001110 '
#1995
b10001111 %
b10001111 )
b10001111 '
#2000
b10010000 %
b10010000 )
b10010000 '
#2005
b10010001 %
b10010001 )
b10010001 '
#2010
b10010010 %
b10010010 )
b10010010 '
#2015
b10010011 %
b10010011 )
b10010011 '
#2020
b10010100 %
b10010100 )
b10010100 '
#2025
b10010101 %
b10010101 )
b10010101 '
#2030
b10010110 %
b10010110 )
b10010110 '
#2035
b10010111 %
b10010111 )
b10010111 '
#2040
b10011000 %
b10011000 )
b10011000 '
#2045
b10011001 %
b10011001 )
b10011001 '
#2050
b10011010 %
b10011010 )
b10011010 '
#2055
b10011011 %
b10011011 )
b10011011 '
#2060
b10011100 %
b10011100 )
b10011100 '
#2065
b10011101 %
b10011101 )
b10011101 '
#2070
b10011110 %
b10011110 )
b10011110 '
#2075
b10011111 %
b10011111 )
b10011111 '
#2080
b10100000 %
b10100000 )
b10100000 '
#2085
b10100001 %
b10100001 )
b10100001 '
#2090
b10100010 %
b10100010 )
b10100010 '
#2095
b10100011 %
b10100011 )
b10100011 '
#2100
b10100100 %
b10100100 )
b10100100 '
#2105
b10100101 %
b10100101 )
b10100101 '
#2110
b10100110 %
b10100110 )
b10100110 '
#2115
b10100111 %
b10100111 )
b10100111 '
#2120
b10101000 %
b10101000 )
b10101000 '
#2125
b10101001 %
b10101001 )
b10101001 '
#2130
b10101010 %
b10101010 )
b10101010 '
#2135
b10101011 %
b10101011 )
b10101011 '
#2140
b10101100 %
b10101100 )
b10101100 '
#2145
b10101101 %
b10101101 )
b10101101 '
#2150
b10101110 %
b10101110 )
b10101110 '
#2155
b10101111 %
b10101111 )
b10101111 '
#2160
b10110000 %
b10110000 )
b10110000 '
#2165
b10110001 %
b10110001 )
b10110001 '
#2170
b10110010 %
b10110010 )
b10110010 '
#2175
b10110011 %
b10110011 )
b10110011 '
#2180
b10110100 %
b10110100 )
b10110100 '
#2185
b10110101 %
b10110101 )
b10110101 '
#2190
b10110110 %
b10110110 )
b10110110 '
#2195
b10110111 %
b10110111 )
b10110111 '
#2200
b10111000 %
b10111000 )
b10111000 '
#2205
b10111001 %
b10111001 )
b10111001 '
#2210
b10111010 %
b10111010 )
b10111010 '
#2215
b10111011 %
b10111011 )
b10111011 '
#2220
b10111100 %
b10111100 )
b10111100 '
#2225
b10111101 %
b10111101 )
b10111101 '
#2230
b10111110 %
b10111110 )
b10111110 '
#2235
b10111111 %
b10111111 )
b10111111 '
#2240
b11000000 %
b11000000 )
b11000000 '
#2245
b11000001 %
b11000001 )
b11000001 '
#2250
b11000010 %
b11000010 )
b11000010 '
#2255
b11000011 %
b11000011 )
b11000011 '
#2260
b11000100 %
b11000100 )
b11000100 '
#2265
b11000101 %
b11000101 )
b11000101 '
#2270
b11000110 %
b11000110 )
b11000110 '
#2275
b11000111 %
b11000111 )
b11000111 '
#2280
b11001000 %
b11001000 )
b11001000 '
#2285
b11001001 %
b11001001 )
b11001001 '
#2290
b11001010 %
b11001010 )
b11001010 '
#2295
b11001011 %
b11001011 )
b11001011 '
#2300
b11001100 %
b11001100 )
b11001100 '
#2305
b11001101 %
b11001101 )
b11001101 '
#2310
b11001110 %
b11001110 )
b11001110 '
#2315
b11001111 %
b11001111 )
b11001111 '
#2320
b11010000 %
b11010000 )
b11010000 '
#2325
b11010001 %
b11010001 )
b11010001 '
#2330
b11010010 %
b11010010 )
b11010010 '
#2335
b11010011 %
b11010011 )
b11010011 '
#2340
b11010100 %
b11010100 )
b11010100 '
#2345
b11010101 %
b11010101 )
b11010101 '
#2350
b11010110 %
b11010110 )
b11010110 '
#2355
b11010111 %
b11010111 )
b11010111 '
#2360
b11011000 %
b11011000 )
b11011000 '
#2365
b11011001 %
b11011001 )
b11011001 '
#2370
b11011010 %
b11011010 )
b11011010 '
#2375
b11011011 %
b11011011 )
b11011011 '
#2380
b11011100 %
b11011100 )
b11011100 '
#2385
b11011101 %
b11011101 )
b11011101 '
#2390
b11011110 %
b11011110 )
b11011110 '
#2395
b11011111 %
b11011111 )
b11011111 '
#2400
b11100000 %
b11100000 )
b11100000 '
#2405
b11100001 %
b11100001 )
b11100001 '
#2410
b11100010 %
b11100010 )
b11100010 '
#2415
b11100011 %
b11100011 )
b11100011 '
#2420
b11100100 %
b11100100 )
b11100100 '
#2425
b11100101 %
b11100101 )
b11100101 '
#2430
b11100110 %
b11100110 )
b11100110 '
#2435
b11100111 %
b11100111 )
b11100111 '
#2440
b11101000 %
b11101000 )
b11101000 '
#2445
b11101001 %
b11101001 )
b11101001 '
#2450
b11101010 %
b11101010 )
b11101010 '
#2455
b11101011 %
b11101011 )
b11101011 '
#2460
b11101100 %
b11101100 )
b11101100 '
#2465
b11101101 %
b11101101 )
b11101101 '
#2470
b11101110 %
b11101110 )
b11101110 '
#2475
b11101111 %
b11101111 )
b11101111 '
#2480
b11110000 %
b11110000 )
b11110000 '
#2485
b11110001 %
b11110001 )
b11110001 '
#2490
b11110010 %
b11110010 )
b11110010 '
#2495
b11110011 %
b11110011 )
b11110011 '
#2500
b11110100 %
b11110100 )
b11110100 '
#2505
b11110101 %
b11110101 )
b11110101 '
#2510
b11110110 %
b11110110 )
b11110110 '
#2515
b11110111 %
b11110111 )
b11110111 '
#2520
b11111000 %
b11111000 )
b11111000 '
#2525
b11111001 %
b11111001 )
b11111001 '
#2530
b11111010 %
b11111010 )
b11111010 '
#2535
b11111011 %
b11111011 )
b11111011 '
#2540
b11111100 %
b11111100 )
b11111100 '
#2545
b11111101 %
b11111101 )
b11111101 '
#2550
b11111110 %
b11111110 )
b11111110 '
#2555
b11111111 %
b11111111 )
b11111111 '
#2560
1#
0"
b0 %
b0 )
b10 $
b10 (
b10 &
b0 '
#2565
b1 %
b1 )
b1 '
#2570
0#
1!
b10 %
b10 )
b10 '
#2575
1"
0!
b11 %
b11 )
b11 '
#2580
b100 %
b100 )
b100 '
#2585
b101 %
b101 )
b101 '
#2590
b110 %
b110 )
b110 '
#2595
b111 %
b111 )
b111 '
#2600
b1000 %
b1000 )
b1000 '
#2605
b1001 %
b1001 )
b1001 '
#2610
b1010 %
b1010 )
b1010 '
#2615
b1011 %
b1011 )
b1011 '
#2620
b1100 %
b1100 )
b1100 '
#2625
b1101 %
b1101 )
b1101 '
#2630
b1110 %
b1110 )
b1110 '
#2635
b1111 %
b1111 )
b1111 '
#2640
b10000 %
b10000 )
b10000 '
#2645
b10001 %
b10001 )
b10001 '
#2650
b10010 %
b10010 )
b10010 '
#2655
b10011 %
b10011 )
b10011 '
#2660
b10100 %
b10100 )
b10100 '
#2665
b10101 %
b10101 )
b10101 '
#2670
b10110 %
b10110 )
b10110 '
#2675
b10111 %
b10111 )
b10111 '
#2680
b11000 %
b11000 )
b11000 '
#2685
b11001 %
b11001 )
b11001 '
#2690
b11010 %
b11010 )
b11010 '
#2695
b11011 %
b11011 )
b11011 '
#2700
b11100 %
b11100 )
b11100 '
#2705
b11101 %
b11101 )
b11101 '
#2710
b11110 %
b11110 )
b11110 '
#2715
b11111 %
b11111 )
b11111 '
#2720
b100000 %
b100000 )
b100000 '
#2725
b100001 %
b100001 )
b100001 '
#2730
b100010 %
b100010 )
b100010 '
#2735
b100011 %
b100011 )
b100011 '
#2740
b100100 %
b100100 )
b100100 '
#2745
b100101 %
b100101 )
b100101 '
#2750
b100110 %
b100110 )
b100110 '
#2755
b100111 %
b100111 )
b100111 '
#2760
b101000 %
b101000 )
b101000 '
#2765
b101001 %
b101001 )
b101001 '
#2770
b101010 %
b101010 )
b101010 '
#2775
b101011 %
b101011 )
b101011 '
#2780
b101100 %
b101100 )
b101100 '
#2785
b101101 %
b101101 )
b101101 '
#2790
b101110 %
b101110 )
b101110 '
#2795
b101111 %
b101111 )
b101111 '
#2800
b110000 %
b110000 )
b110000 '
#2805
b110001 %
b110001 )
b110001 '
#2810
b110010 %
b110010 )
b110010 '
#2815
b110011 %
b110011 )
b110011 '
#2820
b110100 %
b110100 )
b110100 '
#2825
b110101 %
b110101 )
b110101 '
#2830
b110110 %
b110110 )
b110110 '
#2835
b110111 %
b110111 )
b110111 '
#2840
b111000 %
b111000 )
b111000 '
#2845
b111001 %
b111001 )
b111001 '
#2850
b111010 %
b111010 )
b111010 '
#2855
b111011 %
b111011 )
b111011 '
#2860
b111100 %
b111100 )
b111100 '
#2865
b111101 %
b111101 )
b111101 '
#2870
b111110 %
b111110 )
b111110 '
#2875
b111111 %
b111111 )
b111111 '
#2880
b1000000 %
b1000000 )
b1000000 '
#2885
b1000001 %
b1000001 )
b1000001 '
#2890
b1000010 %
b1000010 )
b1000010 '
#2895
b1000011 %
b1000011 )
b1000011 '
#2900
b1000100 %
b1000100 )
b1000100 '
#2905
b1000101 %
b1000101 )
b1000101 '
#2910
b1000110 %
b1000110 )
b1000110 '
#2915
b1000111 %
b1000111 )
b1000111 '
#2920
b1001000 %
b1001000 )
b1001000 '
#2925
b1001001 %
b1001001 )
b1001001 '
#2930
b1001010 %
b1001010 )
b1001010 '
#2935
b1001011 %
b1001011 )
b1001011 '
#2940
b1001100 %
b1001100 )
b1001100 '
#2945
b1001101 %
b1001101 )
b1001101 '
#2950
b1001110 %
b1001110 )
b1001110 '
#2955
b1001111 %
b1001111 )
b1001111 '
#2960
b1010000 %
b1010000 )
b1010000 '
#2965
b1010001 %
b1010001 )
b1010001 '
#2970
b1010010 %
b1010010 )
b1010010 '
#2975
b1010011 %
b1010011 )
b1010011 '
#2980
b1010100 %
b1010100 )
b1010100 '
#2985
b1010101 %
b1010101 )
b1010101 '
#2990
b1010110 %
b1010110 )
b1010110 '
#2995
b1010111 %
b1010111 )
b1010111 '
