DAY2/four_out_demux/four_out_demux.v
module four_out_demux(o1,o2,o3,o4,a,s0,s1);

input a;
input s0,s1;
output o1,o2,o3,o4;

assign o1=~s0&~s1&a;
assign o2=~s0&s1&a;
assign o3=s0&~s1&a;
assign o4=s0&s1&a;
endmodule

/*GATE LEVEL MODELING

 not(s0_c,s0); 
 not(s1_c,s1);
 
 and(o1,s0_c,s1_c,a);
 and(o2,s0_c,s1,a);
 and(o3,s0,s1_c,a);
 and(o4,s0,s1,a);

 *BEHAVIORAL MODELING


module four_out_demux(o1,o2,o3,o4,a,s0,s1);

input a;
input s0,s1;
output o1,o2,o3,o4;

reg(a,s0,s1);

if({s0,s1}==2'b00)
	01=a;
if else({s0,s1}==2'b01)
        02=a;
if else({s0,s1}==2'b10)
        03=a;
if else({s0,s1}==2'b11)
        04=a;
end 
endmodule

DAY2/four_out_demux/four_out_demux_tb.v
module four_out_demux_tb;
reg a;
reg s0,s1;
wire o1,o2,o3,o4;

four_out_demux dut(.a(a),.s0(s0),.s1(s1),.o1(o1),.o2(o2),.o3(o3),.o4(o4));

initial begin
$monitor("a=%b s0=%b s1=%b  o1=%b o2=%b o3=%b o4=%b",a,s0,s1,o1,o2,o3,o4);
$dumpfile("four_out_demux_wave");
$dumpvars(0,four_out_demux_tb);

a=0;s0=0;s1=0;
#8 a=0;s0=0;s1=1;
#8 a=0;s0=1;s1=0;
#8 a=0;s0=1;s1=1;
#8 a=1;s0=0;s1=0;
#8 a=1;s0=0;s1=1;
#8 a=1;s0=1;s1=0;
#8 a=1;s0=1;s1=1;
#8;
end
endmodule

DAY2/four_out_demux/four_out_demux_wave.vcd
$date
	Sat Oct 11 09:57:57 2025
$end
$version
	Icarus Verilog
$end
$timescale
	1s
$end
$scope module four_out_demux_tb $end
$var wire 1 ! o4 $end
$var wire 1 " o3 $end
$var wire 1 # o2 $end
$var wire 1 $ o1 $end
$var reg 1 % a $end
$var reg 1 & s0 $end
$var reg 1 ' s1 $end
$scope module dut $end
$var wire 1 % a $end
$var wire 1 $ o1 $end
$var wire 1 # o2 $end
$var wire 1 " o3 $end
$var wire 1 ! o4 $end
$var wire 1 & s0 $end
$var wire 1 ' s1 $end
$upscope $end
$upscope $end
$enddefinitions $end
$comment Show the parameter values. $end
$dumpall
$end
#0
$dumpvars
0'
0&
0%
0$
0#
0"
0!
$end
#8
1'
#16
0'
1&
#24
1'
#32
1$
0!
0'
0&
1%
#40
0$
1#
1'
#48
1"
0#
0'
1&
#56
0"
1!
1'
