DAY4/priority_encoder.v
module priority_encoder(input d3,d2,d1,d0,output [1:0]a,output v);

assign v= d3|d2|d1|d0;
assign a[1] = d3 | (d2 & ~d3);
assign a[0] = d3 | (d1 & ~d3 & ~d2);

endmodule

DAY4/priority_encoder_tb.v
module priority_encoder_tb;

reg d3,d2,d1,d0;
wire [1:0]a;
wire v;
integer i;

priority_encoder uut(.d3(d3),.d2(d2),.d1(d1),.d0(d0),.a(a),.v(v));

initial begin
$monitor("d3=%b d2=%b d1=%b d0=%b a=%b v=%b",d3,d2,d1,d0,a,v);
$dumpfile("priority_encoder_wave.vcd");
$dumpvars(0,priority_encoder_tb);

for(i=0; i<16; i=i+1)begin
{d3,d2,d1,d0}=i;
#10;
end
$finish;
end
endmodule

DAY4/priority_encoder_wave.vcd
$date
	Mon Oct 13 21:41:09 2025
$end
$version
	Icarus Verilog
$end
$timescale
	1s
$end
$scope module priority_encoder_tb $end
$var wire 1 ! v $end
$var wire 2 " a [1:0] $end
$var reg 1 # d0 $end
$var reg 1 $ d1 $end
$var reg 1 % d2 $end
$var reg 1 & d3 $end
$var integer 32 ' i [31:0] $end
$scope module uut $end
$var wire 1 # d0 $end
$var wire 1 $ d1 $end
$var wire 1 % d2 $end
$var wire 1 & d3 $end
$var wire 1 ! v $end
$var wire 2 ( a [1:0] $end
$upscope $end
$upscope $end
$enddefinitions $end
$comment Show the parameter values. $end
$dumpall
$end
#0
$dumpvars
b0 (
b0 '
0&
0%
0$
0#
b0 "
0!
$end
#10
1!
1#
b1 '
#20
b1 "
b1 (
1!
1$
0#
b10 '
#30
1#
b11 '
#40
b10 "
b10 (
1!
1%
0$
0#
b100 '
#50
1#
b101 '
#60
1$
0#
b110 '
#70
1#
b111 '
#80
b11 "
b11 (
1&
0%
0$
0#
b1000 '
#90
1#
b1001 '
#100
1$
0#
b1010 '
#110
1#
b1011 '
#120
1%
0$
0#
b1100 '
#130
1#
b1101 '
#140
1$
0#
b1110 '
#150
1#
b1111 '
#160
b10000 '
