DAY1/full_sub/full_sub.v
module full_sub(input a,b,c,output diff,borr);
assign diff=a^b^c;
assign borr=(~a&b)|(c&~a)|(c&~b);
endmodule

DAY1/full_sub/full_sub_tb.v
module full_sub_tb();
reg a,b,c;
wire diff,borr;
full_sub dut(.a(a),.b(b),.c(c),.diff(diff),.borr(borr));

initial begin
$monitor("Time=%0t a=%b b=%b c=%b diff=%b borr=%b",$time,a,b,c,diff,borr);
$dumpfile("full_sub_wave.vcd");
$dumpvars(8,full_sub_tb);

a=0;b=0;c=0;
#10 a=0;b=0;c=1;
#10 a=0;b=1;c=0;
#10 a=0;b=1;c=1;
#10 a=1;b=0;c=0;
#10 a=1;b=0;c=1;
#10 a=1;b=1;c=0;
#10 a=1;b=1;c=1;
#10;
$finish;
end
endmodule

DAY1/full_sub/full_sub_wave.vcd
$date
	Fri Oct 10 05:40:36 2025
$end
$version
	Icarus Verilog
$end
$timescale
	1s
$end
$scope module full_sub_tb $end
$var wire 1 ! diff $end
$var wire 1 " borr $end
$var reg 1 # a $end
$var reg 1 $ b $end
$var reg 1 % c $end
$scope module dut $end
$var wire 1 # a $end
$var wire 1 $ b $end
$var wire 1 " borr $end
$var wire 1 % c $end
$var wire 1 ! diff $end
$upscope $end
$upscope $end
$enddefinitions $end
$comment Show the parameter values. $end
$dumpall
$end
#0
$dumpvars
0%
0$
0#
0"
0!
$end
#10
1"
1!
1%
#20
0%
1$
#30
0!
1%
#40
0"
1!
0%
0$
1#
#50
1"
0!
1%
#60
0"
0%
1$
#70
1!
1%
