DAY3/BINARY_to_GRAY/BINARY_to_GRAY.v
module BINARY_to_GRAY(g3,g2,g1,g0,b3,b2,b1,b0);
input b3,b2,b1,b0;
output g3,g2,g1,g0;

assign g3=b3;
assign g2=b3^b2;
assign g1=b2^b1;
assign g0=b1^b0;

endmodule

DAY3/BINARY_to_GRAY/BINARY_to_GRAY_tb.v
module BINARY_to_GRAY_tb;
reg b3,b2,b1,b0;
wire g3,g2,g1,g0;

BINARY_to_GRAY uut(.b3(b3),.b2(b2),.b1(b1),.b0(b0),.g3(g3),.g2(g2),.g1(g1),.g0(g0));


initial begin
$monitor("Time=%0t |b3=%b |b2=%b |b1=%b |b0=%b |g3=%b |g2=%b |g1=%b |g0=%b",$time,b3,b2,b1,b0,g3,g2,g1,g0);
$dumpfile("BINARY_to_GRAY_wave.vcd");
$dumpvars(0,BINARY_to_GRAY_tb);

 b3=0;b2=0;b1=0;b0=0; 
#5 b3=0;b2=0;b1=0;b0=1; 
#5 b3=0;b2=0;b1=1;b0=0; 
#5 b3=0;b2=0;b1=1;b0=1; 
#5 b3=0;b2=1;b1=0;b0=0; 
#5 b3=0;b2=1;b1=0;b0=1; 
#5 b3=0;b2=1;b1=1;b0=0; 
#5 b3=0;b2=1;b1=1;b0=1; 
#5 b3=1;b2=0;b1=0;b0=0; 
#5 b3=1;b2=0;b1=0;b0=1; 
#5 b3=1;b2=0;b1=1;b0=0; 
#5 b3=1;b2=0;b1=1;b0=1; 
#5 b3=1;b2=1;b1=0;b0=0; 
#5 b3=1;b2=1;b1=0;b0=1; 
#5 b3=1;b2=1;b1=1;b0=0; 
#5 b3=1;b2=1;b1=1;b0=1; 
#5;
end
endmodule

DAY3/BINARY_to_GRAY/BINARY_to_GRAY_wave.vcd
$date
	Mon Oct 13 20:01:51 2025
$end
$version
	Icarus Verilog
$end
$timescale
	1s
$end
$scope module BINARY_to_GRAY_tb $end
$var wire 1 ! g3 $end
$var wire 1 " g2 $end
$var wire 1 # g1 $end
$var wire 1 $ g0 $end
$var reg 1 % b0 $end
$var reg 1 & b1 $end
$var reg 1 ' b2 $end
$var reg 1 ( b3 $end
$scope module uut $end
$var wire 1 % b0 $end
$var wire 1 & b1 $end
$var wire 1 ' b2 $end
$var wire 1 ( b3 $end
$var wire 1 $ g0 $end
$var wire 1 # g1 $end
$var wire 1 " g2 $end
$var wire 1 ! g3 $end
$upscope $end
$upscope $end
$enddefinitions $end
$comment Show the parameter values. $end
$dumpall
$end
#0
$dumpvars
0(
0'
0&
0%
0$
0#
0"
0!
$end
#5
1$
1%
#10
1#
0%
1&
#15
0$
1%
#20
1"
0%
0&
1'
#25
1$
1%
#30
0#
0%
1&
#35
0$
1%
#40
0%
0&
0'
1!
1(
#45
1$
1%
#50
1#
0%
1&
#55
0$
1%
#60
0"
0%
0&
1'
#65
1$
1%
#70
0#
0%
1&
#75
0$
1%
