DAY3/BINARY_to_EXCESS-3/BINARY_to_EXCESS-3.v
module BINARY_to_EXCESS_3(x,a);
input [3:0]a;
output [3:0]x;

assign x = a + 4'b0011;
endmodule

DAY3/BINARY_to_EXCESS-3/BINARY_to_EXCESS-3_tb.v
module BINARY_to_EXCESS_3_tb;

reg [3:0]a;
wire [3:0]x;
integer i;

BINARY_to_EXCESS_3 uut(.x(x),.a(a));

initial begin
$monitor("Time=%0t | a=%b | x=%b",$time,a,x);
$dumpfile("BINARY_to_EXCESS_3_wave.vcd");
$dumpvars(0,BINARY_to_EXCESS_3_tb);

for(i=0; i<16; i= i+1)begin
a=i;
#10;
end
$finish;
end
endmodule

DAY3/BINARY_to_EXCESS-3/BINARY_to_EXCESS_3_wave.vcd
$date
	Mon Oct 13 10:02:50 2025
$end
$version
	Icarus Verilog
$end
$timescale
	1s
$end
$scope module BINARY_to_EXCESS_3_tb $end
$var wire 4 ! x [3:0] $end
$var reg 4 " a [3:0] $end
$var integer 32 # i [31:0] $end
$scope module uut $end
$var wire 4 $ a [3:0] $end
$var wire 4 % x [3:0] $end
$upscope $end
$upscope $end
$enddefinitions $end
$comment Show the parameter values. $end
$dumpall
$end
#0
$dumpvars
b11 %
b0 $
b0 #
b0 "
b11 !
$end
#10
b100 !
b100 %
b1 "
b1 $
b1 #
#20
b101 !
b101 %
b10 "
b10 $
b10 #
#30
b110 !
b110 %
b11 "
b11 $
b11 #
#40
b111 !
b111 %
b100 "
b100 $
b100 #
#50
b1000 !
b1000 %
b101 "
b101 $
b101 #
#60
b1001 !
b1001 %
b110 "
b110 $
b110 #
#70
b1010 !
b1010 %
b111 "
b111 $
b111 #
#80
b1011 !
b1011 %
b1000 "
b1000 $
b1000 #
#90
b1100 !
b1100 %
b1001 "
b1001 $
b1001 #
#100
b1101 !
b1101 %
b1010 "
b1010 $
b1010 #
#110
b1110 !
b1110 %
b1011 "
b1011 $
b1011 #
#120
b1111 !
b1111 %
b1100 "
b1100 $
b1100 #
#130
b0 !
b0 %
b1101 "
b1101 $
b1101 #
#140
b1 !
b1 %
b1110 "
b1110 $
b1110 #
#150
b10 !
b10 %
b1111 "
b1111 $
b1111 #
#160
b10000 #
