DAY2/decoder_3_to_8/decoder_3_to_8.v
module decoder_3_to_8(o1,o2,o3,o4,o5,o6,o7,o8,a,b,c);
input a,b,c;
output o1,o2,o3,o4,o5,o6,o7,o8;

assign o1= ~a&~b&~c;
assign o2= ~a&~b&c;
assign o3= ~a&b&~c;
assign o4= ~a&b&c;
assign o5= a&~b&~c;
assign o6= a&~b&c;
assign o7= a&b&~c;
assign o8= a&b&c;

endmodule

DAY2/decoder_3_to_8/decoder_3_to_8_tb.v
module decoder_3_to_8_tb;

reg a,b,c;
wire o1,o2,o3,o4,o5,o6,o7,o8;

decoder_3_to_8 uut(.a(a),
                   .b(b),
                   .c(c),
                   .o1(o1),
                   .o2(o2),
                   .o3(o3),
                   .o4(o4),
                   .o5(o5),
                   .o6(o6),
                   .o7(o7),
                   .o8(o8));

initial begin
$monitor("a=%b b=%b c=%b o1=%b o2=%b o3=%b o4=%b o5=%b o6=%b o7=%b o8=%b",a,b,c,o1,o2,o3,o4,o5,o6,o7,o8);
$dumpfile("decoder_3_to_8_wave.vcd");
$dumpvars;

a=0;b=0;c=0;
#2 a=0;b=0;c=1;
#2 a=0;b=1;c=0;
#2 a=0;b=1;c=1;
#2 a=1;b=0;c=0;
#2 a=1;b=0;c=1;
#2 a=1;b=1;c=0;
#2 a=1;b=1;c=1;
#2;
$finish;
end
endmodule

DAY2/decoder_3_to_8/decoder_3_to_8_wave.vcd
$date
	Sun Oct 12 12:56:12 2025
$end
$version
	Icarus Verilog
$end
$timescale
	1s
$end
$scope module decoder_3_to_8_tb $end
$var wire 1 ! o8 $end
$var wire 1 " o7 $end
$var wire 1 # o6 $end
$var wire 1 $ o5 $end
$var wire 1 % o4 $end
$var wire 1 & o3 $end
$var wire 1 ' o2 $end
$var wire 1 ( o1 $end
$var reg 1 ) a $end
$var reg 1 * b $end
$var reg 1 + c $end
$scope module uut $end
$var wire 1 ) a $end
$var wire 1 * b $end
$var wire 1 + c $end
$var wire 1 ( o1 $end
$var wire 1 ' o2 $end
$var wire 1 & o3 $end
$var wire 1 % o4 $end
$var wire 1 $ o5 $end
$var wire 1 # o6 $end
$var wire 1 " o7 $end
$var wire 1 ! o8 $end
$upscope $end
$upscope $end
$enddefinitions $end
$comment Show the parameter values. $end
$dumpall
$end
#0
$dumpvars
0+
0*
0)
1(
0'
0&
0%
0$
0#
0"
0!
$end
#2
0(
1'
1+
#4
1&
0'
0+
1*
#6
0&
1%
1+
#8
1$
0%
0+
0*
1)
#10
0$
1#
1+
#12
1"
0#
0+
1*
#14
0"
1!
1+
