DAY2/BCD_to_GRAY/BCD_to_GRAY.v
module BCD_to_GRAY(g3,g2,g1,g0,b3,b2,b1,b0);
input b3,b2,b1,b0;
output g3,g2,g1,g0;

assign g3= b3;
assign g2= b3^b2;
assign g1= b2^b1;
assign g0= b1^b0;

endmodule

DAY2/BCD_to_GRAY/BCD_to_GRAY_tb.v
module BCD_to_GRAY_tb;

reg b3,b2,b1,b0;
wire g3,g2,g1,g0;

BCD_to_GRAY dut(.b3(b3),.b2(b2),.b1(b1),.b0(b0),.g3(g3),.g2(g2),.g1(g1),.g0(g0));     

initial begin
$monitor("b3=%b b2=%b b1=%b b0=%b g3=%b g2=%b g1=%b g0=%b",b3,b2,b1,b0,g3,g2,g1,g0);
$dumpfile("BCD_to_GRAY_wave.vcd");
$dumpvars(0,BCD_to_GRAY_tb);

initial begin
for(i=0; i<10; i=i+1) begin
{b3,b2,b1,b0} = i;
#5;
end    
end 
endmodule

DAY2/BCD_to_GRAY/BCD_to_GRAY_wave.vcd
$date
	Sun Oct 12 14:49:01 2025
$end
$version
	Icarus Verilog
$end
$timescale
	1s
$end
$scope module BCD_to_GRAY_tb $end
$var wire 1 ! g3 $end
$var wire 1 " g2 $end
$var wire 1 # g1 $end
$var wire 1 $ g0 $end
$var reg 1 % b0 $end
$var reg 1 & b1 $end
$var reg 1 ' b2 $end
$var reg 1 ( b3 $end
$scope module dut $end
$var wire 1 % b0 $end
$var wire 1 & b1 $end
$var wire 1 ' b2 $end
$var wire 1 ) b3 $end
$var wire 1 $ g0 $end
$var wire 1 # g1 $end
$var wire 1 " g2 $end
$var wire 1 ! g3 $end
$upscope $end
$upscope $end
$enddefinitions $end
$comment Show the parameter values. $end
$dumpall
$end
#0
$dumpvars
z)
0(
0'
0&
0%
0$
0#
x"
z!
$end
#5
1(
#10
1#
0(
1'
#15
1(
#20
1$
0(
0'
1&
#25
1(
#30
0#
0(
1'
#35
1(
#40
0(
0'
0&
1%
#45
1(
