DAY3/BINARY_to_7_SEGMENT/BINARY_to_7_SEGMENT.v
module BINARY_to_7_SEGMENT(d,b);
input [3:0]b;
output reg[6:0]d;

always@(*)begin
 case(b)

4'b0000:d=7'b1111110;
4'b0001:d=7'b0110000;
4'b0010:d=7'b1101101;
4'b0011:d=7'b1111001;
4'b0100:d=7'b0111011;
4'b0101:d=7'b1011111;
4'b0110:d=7'b1110000;
4'b0111:d=7'b1111000;
4'b1000:d=7'b1111111;
4'b1001:d=7'b1111011;
default:d=7'b0000001;
endcase
end
endmodule

DAY3/BINARY_to_7_SEGMENT/BINARY_to_7_SEGMENT_tb.v
module BINARY_to_7_SEGMENT_tb;

reg [3:0]b;
wire [6:0]d;
integer i;

BINARY_to_7_SEGMENT dut(.b(b),.d(d));

initial begin
$monitor("Time=%0t b=%b d=%b",$time,b,d);
$dumpfile("BINARY_to_7_SEGMENT_wave.vcd");
$dumpvars(0,BINARY_to_7_SEGMENT_tb);

for(i=0; i<10; i=i+1)begin
b=i;
#10;
end
$finish;
end
endmodule

DAY3/BINARY_to_7_SEGMENT/BINARY_to_7_SEGMENT_wave.vcd
$date
	Mon Oct 13 13:51:00 2025
$end
$version
	Icarus Verilog
$end
$timescale
	1s
$end
$scope module BINARY_to_7_SEGMENT_tb $end
$var wire 7 ! d [6:0] $end
$var reg 4 " b [3:0] $end
$var integer 32 # i [31:0] $end
$scope module dut $end
$var wire 4 $ b [3:0] $end
$var reg 7 % d [6:0] $end
$upscope $end
$upscope $end
$enddefinitions $end
$comment Show the parameter values. $end
$dumpall
$end
#0
$dumpvars
b1111110 %
b0 $
b0 #
b0 "
b1111110 !
$end
#10
b110000 !
b110000 %
b1 "
b1 $
b1 #
#20
b1101101 !
b1101101 %
b10 "
b10 $
b10 #
#30
b1111001 !
b1111001 %
b11 "
b11 $
b11 #
#40
b111011 !
b111011 %
b100 "
b100 $
b100 #
#50
b1011111 !
b1011111 %
b101 "
b101 $
b101 #
#60
b1110000 !
b1110000 %
b110 "
b110 $
b110 #
#70
b1111000 !
b1111000 %
b111 "
b111 $
b111 #
#80
b1111111 !
b1111111 %
b1000 "
b1000 $
b1000 #
#90
b1111011 !
b1111011 %
b1001 "
b1001 $
b1001 #
#100
b1010 #
