DAY3/EXCESS-3_to_BINARY/EXCESS-3_to_BINARY.v
module  EXCESS_3_to_BINARY(a,z);
input [3:0]z;
output [3:0]a;

assign a= z - 4'b0011;

endmodule

DAY3/EXCESS-3_to_BINARY/EXCESS-3_to_BINARY_tb.v
module  EXCESS_3_to_BINARY_tb;

reg [3:0]z;
wire [3:0]a;
integer i;

EXCESS_3_to_BINARY dut(.a(a),.z(z));

initial begin
$monitor("z=%b a=%b",z,a);
$dumpfile("EXCESS_3_to_BINARY_wave.vcd");
$dumpvars(0,EXCESS_3_to_BINARY_tb);

for (i=3; i<15; i=i+1)begin
z=i;
#2;
end
$finish;
end
endmodule

DAY3/EXCESS-3_to_BINARY/EXCESS_3_to_BINARY_wave.vcd
$date
	Mon Oct 13 10:33:08 2025
$end
$version
	Icarus Verilog
$end
$timescale
	1s
$end
$scope module EXCESS_3_to_BINARY_tb $end
$var wire 4 ! a [3:0] $end
$var reg 4 " z [3:0] $end
$var integer 32 # i [31:0] $end
$scope module dut $end
$var wire 4 $ z [3:0] $end
$var wire 4 % a [3:0] $end
$upscope $end
$upscope $end
$enddefinitions $end
$comment Show the parameter values. $end
$dumpall
$end
#0
$dumpvars
b0 %
b11 $
b11 #
b11 "
b0 !
$end
#2
b1 !
b1 %
b100 "
b100 $
b100 #
#4
b10 !
b10 %
b101 "
b101 $
b101 #
#6
b11 !
b11 %
b110 "
b110 $
b110 #
#8
b100 !
b100 %
b111 "
b111 $
b111 #
#10
b101 !
b101 %
b1000 "
b1000 $
b1000 #
#12
b110 !
b110 %
b1001 "
b1001 $
b1001 #
#14
b111 !
b111 %
b1010 "
b1010 $
b1010 #
#16
b1000 !
b1000 %
b1011 "
b1011 $
b1011 #
#18
b1001 !
b1001 %
b1100 "
b1100 $
b1100 #
#20
b1010 !
b1010 %
b1101 "
b1101 $
b1101 #
#22
b1011 !
b1011 %
b1110 "
b1110 $
b1110 #
#24
b1111 #
